open_qbench/__init__.py
open_qbench/application_benchmark.py
open_qbench/fidelities.py
open_qbench/py.typed
open_qbench/utils.py
open_qbench/apps/__init__.py
open_qbench/apps/ghz.py
open_qbench/apps/grover.py
open_qbench/apps/max_cut_orca.py
open_qbench/apps/qaoa.py
open_qbench/apps/qft.py
open_qbench/apps/qsvm.py
open_qbench/apps/toffoli.py
open_qbench/apps/vqe.py
open_qbench/core/__init__.py
open_qbench/core/benchmark.py
open_qbench/core/highlevel_benchmark.py
open_qbench/core/hybrid_benchmark.py
open_qbench/core/lowlevel_benchmark.py
open_qbench/core/manager.py
open_qbench/data/__init__.py
open_qbench/data/mnist_train100.csv
open_qbench/photonics/__init__.py
open_qbench/photonics/photonic_circuit.py
open_qbench/photonics/photonic_gates.py
open_qbench/sampler/__init__.py
open_qbench/sampler/base_sampler.py
open_qbench/sampler/bosonic_sampler.py
open_qbench-0.2.0.dist-info/licenses/LICENSE
open_qbench-0.2.0.dist-info/METADATA
open_qbench-0.2.0.dist-info/WHEEL
open_qbench-0.2.0.dist-info/top_level.txt
open_qbench-0.2.0.dist-info/RECORD
