Metadata-Version: 2.4
Name: open-qbench
Version: 0.2.0
Summary: Package for developing and executing quantum computing benchmarks
Requires-Python: ==3.12.*
License-File: LICENSE
Requires-Dist: qiskit-aer~=0.17
Requires-Dist: qiskit~=1.0
Provides-Extra: vqe
Requires-Dist: qiskit-nature[pyscf]>=0.7.2; extra == "vqe"
Provides-Extra: qsvm
Requires-Dist: scikit-image>=0.25.1; extra == "qsvm"
Provides-Extra: ibm
Requires-Dist: qiskit-ibm-runtime>=0.36.1; extra == "ibm"
Provides-Extra: aqt
Requires-Dist: qiskit-aqt-provider>=1.10.0; extra == "aqt"
Dynamic: license-file
